libgfxd.so
pygfxd.py
pygfxd-1.0.5.dist-info/LICENSE
pygfxd-1.0.5.dist-info/METADATA
pygfxd-1.0.5.dist-info/WHEEL
pygfxd-1.0.5.dist-info/top_level.txt
pygfxd-1.0.5.dist-info/RECORD
