Metadata-Version: 2.1
Name: pygfxd
Version: 1.0.5
Summary: Python bindings for libgfxd
Author: Tharo
License-File: LICENSE
